<?xml version="1.0" encoding="UTF-8"?>
<tv generator-info-name="WebGrab+Plus/w MDB &amp; REX Postprocess -- version V3.1.6.0 -- Jan van Straaten" generator-info-url="http://www.webgrabplus.com">
  <channel id="Canal Uno (Ecuador)">
    <display-name lang="es">Canal Uno (Ecuador)</display-name>
    <url>http://www.gatotv.com</url>
  </channel>
  <channel id="Canal Ecuavisa (Ecuador)">
    <display-name lang="es">Canal Ecuavisa (Ecuador)</display-name>
    <url>http://www.gatotv.com</url>
  </channel>
  <channel id="Canal Ecuavisa Internacional">
    <display-name lang="es">Canal Ecuavisa Internacional</display-name>
    <url>http://www.gatotv.com</url>
  </channel>
  <channel id="Canal Ecuador TV">
    <display-name lang="es">Canal Ecuador TV</display-name>
    <url>http://www.gatotv.com</url>
  </channel>
  <channel id="Canal Frecuencia Latina">
    <display-name lang="es">Canal Frecuencia Latina</display-name>
    <url>http://www.gatotv.com</url>
  </channel>
  <channel id="Canal Teleamazonas ">
    <display-name lang="es">Canal Teleamazonas </display-name>
    <url>http://www.gatotv.com</url>
  </channel>
  <channel id="Canal RTS">
    <display-name lang="es">Canal RTS</display-name>
    <url>http://www.gatotv.com</url>
  </channel>
  <programme start="20210315003000 -0600" stop="20210315020000 -0600" channel="Canal Uno (Ecuador)">
    <title lang="es">Película</title>
  </programme>
  <programme start="20210315020000 -0600" stop="20210315030000 -0600" channel="Canal Uno (Ecuador)">
    <title lang="es">Notas divinas</title>
  </programme>
  <programme start="20210315030000 -0600" stop="20210315050000 -0600" channel="Canal Uno (Ecuador)">
    <title lang="es">Película</title>
  </programme>
  <programme start="20210315050000 -0600" stop="20210315051500 -0600" channel="Canal Uno (Ecuador)">
    <title lang="es">Aquí entre nos</title>
  </programme>
  <programme start="20210315051500 -0600" stop="20210315053000 -0600" channel="Canal Uno (Ecuador)">
    <title lang="es">Descubriendo lo paranormal</title>
  </programme>
  <programme start="20210315053000 -0600" stop="20210315060000 -0600" channel="Canal Uno (Ecuador)">
    <title lang="es">Secretos y misterios</title>
  </programme>
  <programme start="20210315060000 -0600" stop="20210315061500 -0600" channel="Canal Uno (Ecuador)">
    <title lang="es">Notas divinas</title>
  </programme>
  <programme start="20210315061500 -0600" stop="20210315063000 -0600" channel="Canal Uno (Ecuador)">
    <title lang="es">Hola Mauricio</title>
  </programme>
  <programme start="20210315063000 -0600" stop="20210315070000 -0600" channel="Canal Uno (Ecuador)">
    <title lang="es">Iglesia Universal</title>
  </programme>
  <programme start="20210315070000 -0600" stop="20210315080000 -0600" channel="Canal Uno (Ecuador)">
    <title lang="es">Conexión comunitaria</title>
  </programme>
  <programme start="20210315080000 -0600" stop="20210315090000 -0600" channel="Canal Uno (Ecuador)">
    <title lang="es">Conexión comunitaria</title>
  </programme>
  <programme start="20210315090000 -0600" stop="20210315091500 -0600" channel="Canal Uno (Ecuador)">
    <title lang="es">Descubriendo lo paranormal</title>
  </programme>
  <programme start="20210315091500 -0600" stop="20210315100000 -0600" channel="Canal Uno (Ecuador)">
    <title lang="es">Aquí entre nos</title>
  </programme>
  <programme start="20210315100000 -0600" stop="20210315103000 -0600" channel="Canal Uno (Ecuador)">
    <title lang="es">Outlet TV</title>
  </programme>
  <programme start="20210315103000 -0600" stop="20210315104500 -0600" channel="Canal Uno (Ecuador)">
    <title lang="es">Hola Mauricio</title>
  </programme>
  <programme start="20210315104500 -0600" stop="20210315113000 -0600" channel="Canal Uno (Ecuador)">
    <title lang="es">Aquí entre nos</title>
  </programme>
  <programme start="20210315113000 -0600" stop="20210315120000 -0600" channel="Canal Uno (Ecuador)">
    <title lang="es">Promo TV</title>
  </programme>
  <programme start="20210315120000 -0600" stop="20210315133000 -0600" channel="Canal Uno (Ecuador)">
    <title lang="es">Directo al grano con José Delgado</title>
  </programme>
  <programme start="20210315133000 -0600" stop="20210315134500 -0600" channel="Canal Uno (Ecuador)">
    <title lang="es">Secretos y misterios</title>
  </programme>
  <programme start="20210315134500 -0600" stop="20210315140000 -0600" channel="Canal Uno (Ecuador)">
    <title lang="es">Hola Mauricio</title>
  </programme>
  <programme start="20210315140000 -0600" stop="20210315143000 -0600" channel="Canal Uno (Ecuador)">
    <title lang="es">La bella Ceci y el imprudente</title>
  </programme>
  <programme start="20210315143000 -0600" stop="20210315150000 -0600" channel="Canal Uno (Ecuador)">
    <title lang="es">Aquí entre nos</title>
  </programme>
  <programme start="20210315150000 -0600" stop="20210315160000 -0600" channel="Canal Uno (Ecuador)">
    <title lang="es">Educa</title>
  </programme>
  <programme start="20210315160000 -0600" stop="20210315163000 -0600" channel="Canal Uno (Ecuador)">
    <title lang="es">Aquí entre nos</title>
  </programme>
  <programme start="20210315163000 -0600" stop="20210315170000 -0600" channel="Canal Uno (Ecuador)">
    <title lang="es">Hola Mauricio</title>
  </programme>
  <programme start="20210315170000 -0600" stop="20210315180000 -0600" channel="Canal Uno (Ecuador)">
    <title lang="es">La Leyenda de Hao Lan</title>
  </programme>
  <programme start="20210315180000 -0600" stop="20210315183000 -0600" channel="Canal Uno (Ecuador)">
    <title lang="es">Iglesia Universal</title>
  </programme>
  <programme start="20210315183000 -0600" stop="20210315190000 -0600" channel="Canal Uno (Ecuador)">
    <title lang="es">Redux</title>
  </programme>
  <programme start="20210315190000 -0600" stop="20210315200000 -0600" channel="Canal Uno (Ecuador)">
    <title lang="es">Mi Recinto</title>
  </programme>
  <programme start="20210315200000 -0600" stop="20210315210000 -0600" channel="Canal Uno (Ecuador)">
    <title lang="es">Noticiero Uno</title>
  </programme>
  <programme start="20210315210000 -0600" stop="20210315213000 -0600" channel="Canal Uno (Ecuador)">
    <title lang="es">La ronca de oro</title>
  </programme>
  <programme start="20210315213000 -0600" stop="20210315223000 -0600" channel="Canal Uno (Ecuador)">
    <title lang="es">Contigo hasta el fin</title>
  </programme>
  <programme start="20210315223000 -0600" stop="20210315233000 -0600" channel="Canal Uno (Ecuador)">
    <title lang="es">Directo al grano con José Delgado</title>
  </programme>
  <programme start="20210315233000 -0600" stop="20210316000000 -0600" channel="Canal Uno (Ecuador)">
    <title lang="es">Hola Mauricio</title>
  </programme>
  <programme start="20210316170000 -0600" stop="20210316180000 -0600" channel="Canal Uno (Ecuador)">
    <title lang="es">La Leyenda de Hao Lan</title>
  </programme>
  <programme start="20210315003000 -0600" stop="20210315023000 -0600" channel="Canal Ecuavisa (Ecuador)">
    <title lang="es">Dr. House</title>
  </programme>
  <programme start="20210315023000 -0600" stop="20210315040000 -0600" channel="Canal Ecuavisa (Ecuador)">
    <title lang="es">Combo amarillo</title>
  </programme>
  <programme start="20210315040000 -0600" stop="20210315050000 -0600" channel="Canal Ecuavisa (Ecuador)">
    <title lang="es">Así pasa</title>
  </programme>
  <programme start="20210315050000 -0600" stop="20210315055500 -0600" channel="Canal Ecuavisa (Ecuador)">
    <title lang="es">Telenovela</title>
  </programme>
  <programme start="20210315055500 -0600" stop="20210315065500 -0600" channel="Canal Ecuavisa (Ecuador)">
    <title lang="es">Televistazo</title>
  </programme>
  <programme start="20210315065500 -0600" stop="20210315073000 -0600" channel="Canal Ecuavisa (Ecuador)">
    <title lang="es">Contacto directo</title>
  </programme>
  <programme start="20210315073000 -0600" stop="20210315083000 -0600" channel="Canal Ecuavisa (Ecuador)">
    <title lang="es">Televistazo</title>
  </programme>
  <programme start="20210315083000 -0600" stop="20210315093000 -0600" channel="Canal Ecuavisa (Ecuador)">
    <title lang="es">Dulce Venganza</title>
  </programme>
  <programme start="20210315093000 -0600" stop="20210315103000 -0600" channel="Canal Ecuavisa (Ecuador)">
    <title lang="es">Telenovela</title>
  </programme>
  <programme start="20210315103000 -0600" stop="20210315130000 -0600" channel="Canal Ecuavisa (Ecuador)">
    <title lang="es">En Contacto</title>
  </programme>
  <programme start="20210315130000 -0600" stop="20210315140000 -0600" channel="Canal Ecuavisa (Ecuador)">
    <title lang="es">Televistazo</title>
  </programme>
  <programme start="20210315140000 -0600" stop="20210315150000 -0600" channel="Canal Ecuavisa (Ecuador)">
    <title lang="es">Caso Cerrado</title>
  </programme>
  <programme start="20210315150000 -0600" stop="20210315160000 -0600" channel="Canal Ecuavisa (Ecuador)">
    <title lang="es">Educa</title>
  </programme>
  <programme start="20210315160000 -0600" stop="20210315170000 -0600" channel="Canal Ecuavisa (Ecuador)">
    <title lang="es">Soñar No Cuesta Nada</title>
  </programme>
  <programme start="20210315170000 -0600" stop="20210315180000 -0600" channel="Canal Ecuavisa (Ecuador)">
    <title lang="es">Gata Salvaje</title>
  </programme>
  <programme start="20210315180000 -0600" stop="20210315190000 -0600" channel="Canal Ecuavisa (Ecuador)">
    <title lang="es">Telenovela</title>
  </programme>
  <programme start="20210315190000 -0600" stop="20210315200000 -0600" channel="Canal Ecuavisa (Ecuador)">
    <title lang="es">Televistazo</title>
  </programme>
  <programme start="20210315200000 -0600" stop="20210315210000 -0600" channel="Canal Ecuavisa (Ecuador)">
    <title lang="es">Meryem</title>
  </programme>
  <programme start="20210315210000 -0600" stop="20210315220000 -0600" channel="Canal Ecuavisa (Ecuador)">
    <title lang="es">La fuerza del amor</title>
  </programme>
  <programme start="20210315220000 -0600" stop="20210315230000 -0600" channel="Canal Ecuavisa (Ecuador)">
    <title lang="es">Sin Senos Sí Hay Paraíso</title>
    <title lang="xx">Sin Senos Sí Hay Paraíso</title>
    <desc lang="es">Ha llegado la hora de elegir a la joven más bella de la región. La pasarela se ha convertido en un campo de batalla donde habrá muchos aliados y enemigos.</desc>
    <credits>
      <actor>Catherine Siachoque</actor>
      <actor>Fabián Ríos</actor>
      <actor>Carolina Gaitán</actor>
      <actor>Juan Pablo Urrego</actor>
      <actor>Majida Issa</actor>
      <actor>Johanna Fadul</actor>
      <actor>César Mora</actor>
      <actor>Juan Pablo Llano</actor>
      <producer>Nelson Martínez</producer>
      <composer>Robert Taylor</composer>
      <composer>Gustavo Bolívar</composer>
    </credits>
    <date>2016</date>
    <category lang="es">Película</category>
    <icon src="https://imagenes.gatotv.com/categorias/telenovelas/miniatura/sin_senos_si_hay_paraiso.jpg" />
    <rating>
      <value>TV-14</value>
    </rating>
  </programme>
  <programme start="20210315230000 -0600" stop="20210316001500 -0600" channel="Canal Ecuavisa (Ecuador)">
    <title lang="es">Tres familias</title>
  </programme>
  <programme start="20210316230000 -0600" stop="20210317001500 -0600" channel="Canal Ecuavisa (Ecuador)">
    <title lang="es">Tres familias</title>
  </programme>
  <programme start="20210317001500 -0600" stop="20210317023000 -0600" channel="Canal Ecuavisa (Ecuador)">
    <title lang="es">Combo amarillo</title>
  </programme>
  <programme start="20210317023000 -0600" stop="20210317050000 -0600" channel="Canal Ecuavisa (Ecuador)">
    <title lang="es">Así pasa</title>
  </programme>
  <programme start="20210317050000 -0600" stop="20210317055500 -0600" channel="Canal Ecuavisa (Ecuador)">
    <title lang="es">Telenovela</title>
  </programme>
  <programme start="20210317055500 -0600" stop="20210317065500 -0600" channel="Canal Ecuavisa (Ecuador)">
    <title lang="es">Televistazo</title>
  </programme>
  <programme start="20210317065500 -0600" stop="20210317073000 -0600" channel="Canal Ecuavisa (Ecuador)">
    <title lang="es">Contacto directo</title>
  </programme>
  <programme start="20210317073000 -0600" stop="20210317083000 -0600" channel="Canal Ecuavisa (Ecuador)">
    <title lang="es">Televistazo</title>
  </programme>
  <programme start="20210317083000 -0600" stop="20210317093000 -0600" channel="Canal Ecuavisa (Ecuador)">
    <title lang="es">Dulce Venganza</title>
  </programme>
  <programme start="20210317093000 -0600" stop="20210317103000 -0600" channel="Canal Ecuavisa (Ecuador)">
    <title lang="es">Telenovela</title>
  </programme>
  <programme start="20210317103000 -0600" stop="20210317130000 -0600" channel="Canal Ecuavisa (Ecuador)">
    <title lang="es">En Contacto</title>
  </programme>
  <programme start="20210317130000 -0600" stop="20210317140000 -0600" channel="Canal Ecuavisa (Ecuador)">
    <title lang="es">Televistazo</title>
  </programme>
  <programme start="20210317140000 -0600" stop="20210317150000 -0600" channel="Canal Ecuavisa (Ecuador)">
    <title lang="es">Caso Cerrado</title>
  </programme>
  <programme start="20210317150000 -0600" stop="20210317160000 -0600" channel="Canal Ecuavisa (Ecuador)">
    <title lang="es">Educa</title>
  </programme>
  <programme start="20210317160000 -0600" stop="20210317170000 -0600" channel="Canal Ecuavisa (Ecuador)">
    <title lang="es">Soñar No Cuesta Nada</title>
  </programme>
  <programme start="20210317170000 -0600" stop="20210317180000 -0600" channel="Canal Ecuavisa (Ecuador)">
    <title lang="es">Gata Salvaje</title>
  </programme>
  <programme start="20210317180000 -0600" stop="20210317190000 -0600" channel="Canal Ecuavisa (Ecuador)">
    <title lang="es">Telenovela</title>
  </programme>
  <programme start="20210317190000 -0600" stop="20210317200000 -0600" channel="Canal Ecuavisa (Ecuador)">
    <title lang="es">Televistazo</title>
  </programme>
  <programme start="20210317200000 -0600" stop="20210317210000 -0600" channel="Canal Ecuavisa (Ecuador)">
    <title lang="es">Meryem</title>
  </programme>
  <programme start="20210317210000 -0600" stop="20210317220000 -0600" channel="Canal Ecuavisa (Ecuador)">
    <title lang="es">La fuerza del amor</title>
  </programme>
  <programme start="20210317220000 -0600" stop="20210317230000 -0600" channel="Canal Ecuavisa (Ecuador)">
    <title lang="es">Sin Senos Sí Hay Paraíso</title>
    <title lang="xx">Sin Senos Sí Hay Paraíso</title>
    <desc lang="es">Ha llegado la hora de elegir a la joven más bella de la región. La pasarela se ha convertido en un campo de batalla donde habrá muchos aliados y enemigos.</desc>
    <credits>
      <actor>Catherine Siachoque</actor>
      <actor>Fabián Ríos</actor>
      <actor>Carolina Gaitán</actor>
      <actor>Juan Pablo Urrego</actor>
      <actor>Majida Issa</actor>
      <actor>Johanna Fadul</actor>
      <actor>César Mora</actor>
      <actor>Juan Pablo Llano</actor>
      <producer>Nelson Martínez</producer>
      <composer>Robert Taylor</composer>
      <composer>Gustavo Bolívar</composer>
    </credits>
    <date>2016</date>
    <category lang="es">Película</category>
    <icon src="https://imagenes.gatotv.com/categorias/telenovelas/miniatura/sin_senos_si_hay_paraiso.jpg" />
    <rating>
      <value>TV-14</value>
    </rating>
  </programme>
  <programme start="20210315003000 -0600" stop="20210315013000 -0600" channel="Canal Ecuavisa Internacional">
    <title lang="es">Televistazo Domingo</title>
  </programme>
  <programme start="20210315013000 -0600" stop="20210315023000 -0600" channel="Canal Ecuavisa Internacional">
    <title lang="es">Políticamente correcto</title>
  </programme>
  <programme start="20210315023000 -0600" stop="20210315030000 -0600" channel="Canal Ecuavisa Internacional">
    <title lang="es">Pasado y Confeso</title>
  </programme>
  <programme start="20210315030000 -0600" stop="20210315033000 -0600" channel="Canal Ecuavisa Internacional">
    <title lang="es">Crónicas urbanas</title>
  </programme>
  <programme start="20210315033000 -0600" stop="20210315040000 -0600" channel="Canal Ecuavisa Internacional">
    <title lang="es">Crónicas urbanas</title>
  </programme>
  <programme start="20210315040000 -0600" stop="20210315050000 -0600" channel="Canal Ecuavisa Internacional">
    <title lang="es">El más querido</title>
  </programme>
  <programme start="20210315050000 -0600" stop="20210315060000 -0600" channel="Canal Ecuavisa Internacional">
    <title lang="es">Rastros de mentiras</title>
  </programme>
  <programme start="20210315060000 -0600" stop="20210315070000 -0600" channel="Canal Ecuavisa Internacional">
    <title lang="es">Televistazo Al Amanecer Costa</title>
  </programme>
  <programme start="20210315070000 -0600" stop="20210315073000 -0600" channel="Canal Ecuavisa Internacional">
    <title lang="es">Contacto Directo</title>
  </programme>
  <programme start="20210315073000 -0600" stop="20210315083000 -0600" channel="Canal Ecuavisa Internacional">
    <title lang="es">Televistazo en la Comunidad Costa</title>
  </programme>
  <programme start="20210315083000 -0600" stop="20210315090000 -0600" channel="Canal Ecuavisa Internacional">
    <title lang="es">Vive fit</title>
  </programme>
  <programme start="20210315090000 -0600" stop="20210315093000 -0600" channel="Canal Ecuavisa Internacional">
    <title lang="es">Hacia un Nuevo Estilo de Vida</title>
  </programme>
  <programme start="20210315093000 -0600" stop="20210315100000 -0600" channel="Canal Ecuavisa Internacional">
    <title lang="es">Programa Pagado</title>
  </programme>
  <programme start="20210315100000 -0600" stop="20210315103000 -0600" channel="Canal Ecuavisa Internacional">
    <title lang="es">El Combo Amarillo</title>
  </programme>
  <programme start="20210315103000 -0600" stop="20210315130000 -0600" channel="Canal Ecuavisa Internacional">
    <title lang="es">En Contacto</title>
  </programme>
  <programme start="20210315130000 -0600" stop="20210315140000 -0600" channel="Canal Ecuavisa Internacional">
    <title lang="es">Televistazo</title>
  </programme>
  <programme start="20210315140000 -0600" stop="20210315143000 -0600" channel="Canal Ecuavisa Internacional">
    <title lang="es">Vive fit</title>
  </programme>
  <programme start="20210315143000 -0600" stop="20210315160000 -0600" channel="Canal Ecuavisa Internacional">
    <title lang="es">Prueba de amor</title>
  </programme>
  <programme start="20210315160000 -0600" stop="20210315170000 -0600" channel="Canal Ecuavisa Internacional">
    <title lang="es">Rastros de mentiras</title>
  </programme>
  <programme start="20210315170000 -0600" stop="20210315173000 -0600" channel="Canal Ecuavisa Internacional">
    <title lang="es">El Combo Amarillo</title>
  </programme>
  <programme start="20210315173000 -0600" stop="20210315180000 -0600" channel="Canal Ecuavisa Internacional">
    <title lang="es">Programa Pagado</title>
  </programme>
  <programme start="20210315180000 -0600" stop="20210315183000 -0600" channel="Canal Ecuavisa Internacional">
    <title lang="es">Así pasa</title>
  </programme>
  <programme start="20210315183000 -0600" stop="20210315190000 -0600" channel="Canal Ecuavisa Internacional">
    <title lang="es">3 Familias</title>
  </programme>
  <programme start="20210315190000 -0600" stop="20210315200000 -0600" channel="Canal Ecuavisa Internacional">
    <title lang="es">Televistazo</title>
  </programme>
  <programme start="20210315200000 -0600" stop="20210315213000 -0600" channel="Canal Ecuavisa Internacional">
    <title lang="es">Prueba de amor</title>
  </programme>
  <programme start="20210315213000 -0600" stop="20210315223000 -0600" channel="Canal Ecuavisa Internacional">
    <title lang="es">Rastros de mentiras</title>
  </programme>
  <programme start="20210315223000 -0600" stop="20210315230000 -0600" channel="Canal Ecuavisa Internacional">
    <title lang="es">Crónicas urbanas</title>
  </programme>
  <programme start="20210315230000 -0600" stop="20210316000000 -0600" channel="Canal Ecuavisa Internacional">
    <title lang="es">Televistazo</title>
  </programme>
  <programme start="20210316000000 -0600" stop="20210316013000 -0600" channel="Canal Ecuavisa Internacional">
    <title lang="es">Prueba de amor</title>
  </programme>
  <programme start="20210316013000 -0600" stop="20210316020000 -0600" channel="Canal Ecuavisa Internacional">
    <title lang="es">Sin límites</title>
  </programme>
  <programme start="20210316020000 -0600" stop="20210316023000 -0600" channel="Canal Ecuavisa Internacional">
    <title lang="es">Pasado y Confeso</title>
  </programme>
  <programme start="20210316023000 -0600" stop="20210316030000 -0600" channel="Canal Ecuavisa Internacional">
    <title lang="es">Vive verde y rebelde</title>
  </programme>
  <programme start="20210316030000 -0600" stop="20210316033000 -0600" channel="Canal Ecuavisa Internacional">
    <title lang="es">Vive simple</title>
  </programme>
  <programme start="20210316033000 -0600" stop="20210316040000 -0600" channel="Canal Ecuavisa Internacional">
    <title lang="es">Crecer sin límites</title>
  </programme>
  <programme start="20210316040000 -0600" stop="20210316050000 -0600" channel="Canal Ecuavisa Internacional">
    <title lang="es">Hacia un Nuevo Estilo de Vida</title>
  </programme>
  <programme start="20210316173000 -0600" stop="20210316180000 -0600" channel="Canal Ecuavisa Internacional">
    <title lang="es">Programa Pagado</title>
  </programme>
  <programme start="20210317060000 -0600" stop="20210317063000 -0600" channel="Canal Ecuavisa Internacional">
    <title lang="es">Programa Pagado</title>
  </programme>
  <programme start="20210317063000 -0600" stop="20210317073000 -0600" channel="Canal Ecuavisa Internacional">
    <title lang="es">Televistazo</title>
  </programme>
  <programme start="20210317073000 -0600" stop="20210317080000 -0600" channel="Canal Ecuavisa Internacional">
    <title lang="es">Programa Pagado</title>
  </programme>
  <programme start="20210317080000 -0600" stop="20210317083000 -0600" channel="Canal Ecuavisa Internacional">
    <title lang="es">Vive simple</title>
  </programme>
  <programme start="20210317083000 -0600" stop="20210317090000 -0600" channel="Canal Ecuavisa Internacional">
    <title lang="es">El Pan Nuestro</title>
  </programme>
  <programme start="20210317090000 -0600" stop="20210317093000 -0600" channel="Canal Ecuavisa Internacional">
    <title lang="es">Ecuador Olímpico</title>
  </programme>
  <programme start="20210317093000 -0600" stop="20210317100000 -0600" channel="Canal Ecuavisa Internacional">
    <title lang="es">Hablando de Inmigración</title>
  </programme>
  <programme start="20210317100000 -0600" stop="20210317110000 -0600" channel="Canal Ecuavisa Internacional">
    <title lang="es">Esta semana</title>
  </programme>
  <programme start="20210317110000 -0600" stop="20210317120000 -0600" channel="Canal Ecuavisa Internacional">
    <title lang="es">Bsc TV</title>
  </programme>
  <programme start="20210317120000 -0600" stop="20210317123000 -0600" channel="Canal Ecuavisa Internacional">
    <title lang="es">Programa Pagado</title>
  </programme>
  <programme start="20210317123000 -0600" stop="20210317140000 -0600" channel="Canal Ecuavisa Internacional">
    <title lang="es">Lo Mejor De: En Contacto</title>
  </programme>
  <programme start="20210317140000 -0600" stop="20210317143000 -0600" channel="Canal Ecuavisa Internacional">
    <title lang="es">El Combo Amarillo</title>
  </programme>
  <programme start="20210317143000 -0600" stop="20210317150000 -0600" channel="Canal Ecuavisa Internacional">
    <title lang="es">El Combo Amarillo</title>
  </programme>
  <programme start="20210317150000 -0600" stop="20210317153000 -0600" channel="Canal Ecuavisa Internacional">
    <title lang="es">3 Familias</title>
  </programme>
  <programme start="20210317153000 -0600" stop="20210317160000 -0600" channel="Canal Ecuavisa Internacional">
    <title lang="es">3 Familias</title>
  </programme>
  <programme start="20210317160000 -0600" stop="20210317180000 -0600" channel="Canal Ecuavisa Internacional">
    <title lang="es">Rastros de mentiras</title>
  </programme>
  <programme start="20210317180000 -0600" stop="20210317183000 -0600" channel="Canal Ecuavisa Internacional">
    <title lang="es">Vive simple</title>
  </programme>
  <programme start="20210317183000 -0600" stop="20210317190000 -0600" channel="Canal Ecuavisa Internacional">
    <title lang="es">Crecer sin límites</title>
  </programme>
  <programme start="20210317190000 -0600" stop="20210317193000 -0600" channel="Canal Ecuavisa Internacional">
    <title lang="es">Televistazo</title>
  </programme>
  <programme start="20210317193000 -0600" stop="20210317203000 -0600" channel="Canal Ecuavisa Internacional">
    <title lang="es">El más querido</title>
  </programme>
  <programme start="20210317203000 -0600" stop="20210317213000 -0600" channel="Canal Ecuavisa Internacional">
    <title lang="es">Secretos</title>
  </programme>
  <programme start="20210317213000 -0600" stop="20210317220000 -0600" channel="Canal Ecuavisa Internacional">
    <title lang="es">Milagros</title>
  </programme>
  <programme start="20210317220000 -0600" stop="20210317230000 -0600" channel="Canal Ecuavisa Internacional">
    <title lang="es">Esta semana</title>
  </programme>
  <programme start="20210317230000 -0600" stop="20210317233000 -0600" channel="Canal Ecuavisa Internacional">
    <title lang="es">Crónicas urbanas</title>
  </programme>
  <programme start="20210317233000 -0600" stop="20210318000000 -0600" channel="Canal Ecuavisa Internacional">
    <title lang="es">Crónicas urbanas</title>
  </programme>
  <programme start="20210318000000 -0600" stop="20210318003000 -0600" channel="Canal Ecuavisa Internacional">
    <title lang="es">Pasado y Confeso</title>
  </programme>
  <programme start="20210318003000 -0600" stop="20210318030000 -0600" channel="Canal Ecuavisa Internacional">
    <title lang="es">Sin límites</title>
  </programme>
  <programme start="20210318030000 -0600" stop="20210318033000 -0600" channel="Canal Ecuavisa Internacional">
    <title lang="es">Ecuador Olímpico</title>
  </programme>
  <programme start="20210318033000 -0600" stop="20210318040000 -0600" channel="Canal Ecuavisa Internacional">
    <title lang="es">El Pan Nuestro</title>
  </programme>
  <programme start="20210318050000 -0600" stop="20210318060000 -0600" channel="Canal Ecuavisa Internacional">
    <title lang="es">Esta semana</title>
  </programme>
  <programme start="20210318060000 -0600" stop="20210318063000 -0600" channel="Canal Ecuavisa Internacional">
    <title lang="es">Plenitud de Vida</title>
  </programme>
  <programme start="20210318063000 -0600" stop="20210318070000 -0600" channel="Canal Ecuavisa Internacional">
    <title lang="es">Programa Pagado</title>
  </programme>
  <programme start="20210318070000 -0600" stop="20210318073000 -0600" channel="Canal Ecuavisa Internacional">
    <title lang="es">Hablando de Inmigración</title>
  </programme>
  <programme start="20210318073000 -0600" stop="20210318083000 -0600" channel="Canal Ecuavisa Internacional">
    <title lang="es">Bsc TV</title>
  </programme>
  <programme start="20210318083000 -0600" stop="20210318090000 -0600" channel="Canal Ecuavisa Internacional">
    <title lang="es">Energía pilates</title>
  </programme>
  <programme start="20210318090000 -0600" stop="20210318093000 -0600" channel="Canal Ecuavisa Internacional">
    <title lang="es">Del huerto a la mesa</title>
  </programme>
  <programme start="20210318093000 -0600" stop="20210318100000 -0600" channel="Canal Ecuavisa Internacional">
    <title lang="es">Armonías</title>
  </programme>
  <programme start="20210318100000 -0600" stop="20210318110000 -0600" channel="Canal Ecuavisa Internacional">
    <title lang="es">Hacia un Nuevo Estilo de Vida</title>
  </programme>
  <programme start="20210318110000 -0600" stop="20210318120000 -0600" channel="Canal Ecuavisa Internacional">
    <title lang="es">Esta semana</title>
  </programme>
  <programme start="20210318120000 -0600" stop="20210318130000 -0600" channel="Canal Ecuavisa Internacional">
    <title lang="es">Políticamente correcto</title>
  </programme>
  <programme start="20210318130000 -0600" stop="20210318150000 -0600" channel="Canal Ecuavisa Internacional">
    <title lang="es">Rastros de mentiras</title>
  </programme>
  <programme start="20210318150000 -0600" stop="20210318160000 -0600" channel="Canal Ecuavisa Internacional">
    <title lang="es">Secretos</title>
  </programme>
  <programme start="20210318160000 -0600" stop="20210318170000 -0600" channel="Canal Ecuavisa Internacional">
    <title lang="es">Milagros</title>
  </programme>
  <programme start="20210318170000 -0600" stop="20210318173000 -0600" channel="Canal Ecuavisa Internacional">
    <title lang="es">Crónicas urbanas</title>
  </programme>
  <programme start="20210318173000 -0600" stop="20210318180000 -0600" channel="Canal Ecuavisa Internacional">
    <title lang="es">Vive verde y rebelde</title>
  </programme>
  <programme start="20210318180000 -0600" stop="20210318183000 -0600" channel="Canal Ecuavisa Internacional">
    <title lang="es">Vive simple</title>
  </programme>
  <programme start="20210318183000 -0600" stop="20210318190000 -0600" channel="Canal Ecuavisa Internacional">
    <title lang="es">Crecer sin límites</title>
  </programme>
  <programme start="20210318190000 -0600" stop="20210318200000 -0600" channel="Canal Ecuavisa Internacional">
    <title lang="es">Televistazo Domingo</title>
  </programme>
  <programme start="20210318200000 -0600" stop="20210318210000 -0600" channel="Canal Ecuavisa Internacional">
    <title lang="es">Políticamente correcto</title>
  </programme>
  <programme start="20210318210000 -0600" stop="20210318220000 -0600" channel="Canal Ecuavisa Internacional">
    <title lang="es">El más querido</title>
  </programme>
  <programme start="20210318220000 -0600" stop="20210318223000 -0600" channel="Canal Ecuavisa Internacional">
    <title lang="es">Crónicas urbanas</title>
  </programme>
  <programme start="20210315003000 -0600" stop="20210315013000 -0600" channel="Canal Ecuador TV">
    <title lang="es">Fanático</title>
  </programme>
  <programme start="20210315013000 -0600" stop="20210315033000 -0600" channel="Canal Ecuador TV">
    <title lang="es">Café TV</title>
  </programme>
  <programme start="20210315033000 -0600" stop="20210315040000 -0600" channel="Canal Ecuador TV">
    <title lang="es">Próxima parada</title>
  </programme>
  <programme start="20210315040000 -0600" stop="20210315043000 -0600" channel="Canal Ecuador TV">
    <title lang="es">Telediario</title>
  </programme>
  <programme start="20210315043000 -0600" stop="20210315053000 -0600" channel="Canal Ecuador TV">
    <title lang="es">Esta es mi canción</title>
  </programme>
  <programme start="20210315053000 -0600" stop="20210315060000 -0600" channel="Canal Ecuador TV">
    <title lang="es">Noticiero Quichua Willaykuna</title>
  </programme>
  <programme start="20210315060000 -0600" stop="20210315080000 -0600" channel="Canal Ecuador TV">
    <title lang="es">Telediario</title>
  </programme>
  <programme start="20210315080000 -0600" stop="20210315100000 -0600" channel="Canal Ecuador TV">
    <title lang="es">Café TV</title>
  </programme>
  <programme start="20210315100000 -0600" stop="20210315110000 -0600" channel="Canal Ecuador TV">
    <title lang="es">Rodando Ecuador</title>
  </programme>
  <programme start="20210315110000 -0600" stop="20210315120000 -0600" channel="Canal Ecuador TV">
    <title lang="es">Infantiles</title>
  </programme>
  <programme start="20210315120000 -0600" stop="20210315123000 -0600" channel="Canal Ecuador TV">
    <title lang="es">Próxima parada</title>
  </programme>
  <programme start="20210315123000 -0600" stop="20210315130000 -0600" channel="Canal Ecuador TV">
    <title lang="es">Hola,¿qué hace</title>
  </programme>
  <programme start="20210315130000 -0600" stop="20210315140000 -0600" channel="Canal Ecuador TV">
    <title lang="es">Telediario</title>
  </programme>
  <programme start="20210315140000 -0600" stop="20210315145000 -0600" channel="Canal Ecuador TV">
    <title lang="es">Fanático</title>
  </programme>
  <programme start="20210315145000 -0600" stop="20210315150000 -0600" channel="Canal Ecuador TV">
    <title lang="es">Tierra y Mar</title>
  </programme>
  <programme start="20210315150000 -0600" stop="20210315160000 -0600" channel="Canal Ecuador TV">
    <title lang="es">Educa</title>
  </programme>
  <programme start="20210315160000 -0600" stop="20210315163000 -0600" channel="Canal Ecuador TV">
    <title lang="es">Infantiles</title>
  </programme>
  <programme start="20210315163000 -0600" stop="20210315183000 -0600" channel="Canal Ecuador TV">
    <title lang="es">Café TV</title>
  </programme>
  <programme start="20210315183000 -0600" stop="20210315190000 -0600" channel="Canal Ecuador TV">
    <title lang="es">Fanático</title>
  </programme>
  <programme start="20210315190000 -0600" stop="20210315200000 -0600" channel="Canal Ecuador TV">
    <title lang="es">Esta es mi canción</title>
  </programme>
  <programme start="20210315200000 -0600" stop="20210315210000 -0600" channel="Canal Ecuador TV">
    <title lang="es">Telediario</title>
  </programme>
  <programme start="20210315210000 -0600" stop="20210315220000 -0600" channel="Canal Ecuador TV">
    <title lang="es">Desde Cero</title>
  </programme>
  <programme start="20210315220000 -0600" stop="20210315230000 -0600" channel="Canal Ecuador TV">
    <title lang="es">Fanático</title>
  </programme>
  <programme start="20210315230000 -0600" stop="20210316000000 -0600" channel="Canal Ecuador TV">
    <title lang="es">Rodando Ecuador</title>
  </programme>
  <programme start="20210316000000 -0600" stop="20210316003000 -0600" channel="Canal Ecuador TV">
    <title lang="es">Próxima parada</title>
  </programme>
  <programme start="20210316003000 -0600" stop="20210316013000 -0600" channel="Canal Ecuador TV">
    <title lang="es">Telediario</title>
  </programme>
  <programme start="20210316013000 -0600" stop="20210316043000 -0600" channel="Canal Ecuador TV">
    <title lang="es">Café TV</title>
  </programme>
  <programme start="20210316163000 -0600" stop="20210316183000 -0600" channel="Canal Ecuador TV">
    <title lang="es">Café TV</title>
  </programme>
  <programme start="20210315003000 -0600" stop="20210315013000 -0600" channel="Canal Frecuencia Latina">
    <title lang="es">Reporte Semanal</title>
  </programme>
  <programme start="20210315013000 -0600" stop="20210315043000 -0600" channel="Canal Frecuencia Latina">
    <title lang="es">Nutrisa</title>
  </programme>
  <programme start="20210315043000 -0600" stop="20210315050000 -0600" channel="Canal Frecuencia Latina">
    <title lang="es">Escándalo</title>
  </programme>
  <programme start="20210315050000 -0600" stop="20210315060000 -0600" channel="Canal Frecuencia Latina">
    <title lang="es">Despierta 90 Matinal</title>
  </programme>
  <programme start="20210315060000 -0600" stop="20210315070000 -0600" channel="Canal Frecuencia Latina">
    <title lang="es">90 Matinal Nacional</title>
  </programme>
  <programme start="20210315070000 -0600" stop="20210315090000 -0600" channel="Canal Frecuencia Latina">
    <title lang="es">90 Matinal</title>
  </programme>
  <programme start="20210315090000 -0600" stop="20210315120000 -0600" channel="Canal Frecuencia Latina">
    <title lang="es">Mujeres al mando</title>
  </programme>
  <programme start="20210315120000 -0600" stop="20210315143000 -0600" channel="Canal Frecuencia Latina">
    <title lang="es">90 Mediodía</title>
  </programme>
  <programme start="20210315143000 -0600" stop="20210315160000 -0600" channel="Canal Frecuencia Latina">
    <title lang="es">Caso Cerrado</title>
  </programme>
  <programme start="20210315160000 -0600" stop="20210315164500 -0600" channel="Canal Frecuencia Latina">
    <title lang="es">Yo soy Betty, la fea</title>
  </programme>
  <programme start="20210315164500 -0600" stop="20210315173000 -0600" channel="Canal Frecuencia Latina">
    <title lang="es">Guerra de Rosas</title>
  </programme>
  <programme start="20210315173000 -0600" stop="20210315190000 -0600" channel="Canal Frecuencia Latina">
    <title lang="es">Caso Cerrado</title>
  </programme>
  <programme start="20210315190000 -0600" stop="20210315203000 -0600" channel="Canal Frecuencia Latina">
    <title lang="es">90 Central</title>
  </programme>
  <programme start="20210315203000 -0600" stop="20210315220000 -0600" channel="Canal Frecuencia Latina">
    <title lang="es">Yo soy</title>
  </programme>
  <programme start="20210315220000 -0600" stop="20210315230000 -0600" channel="Canal Frecuencia Latina">
    <title lang="es">Matar a Jesús</title>
    <title lang="xx">Matar a Jesús</title>
    <desc lang="es">Una joven de 22 años que tras la muerte de su padre conoce al asesino, a partir de ese momento se verá forzada a definir los límites de su propia humanidad.</desc>
    <credits>
      <actor>Natasha Jaramillo</actor>
      <actor>Giovanny Rodríguez</actor>
      <actor>Camilo Escobar</actor>
      <actor>Carmenza Cossio</actor>
      <actor>Juan Pablo Trujillo</actor>
      <actor>José David Medina</actor>
      <actor>Juan Camilo Cárdenas</actor>
    </credits>
    <date>2018</date>
    <category lang="es">Película</category>
    <icon src="https://imagenes.gatotv.com/categorias/peliculas/miniatura/matar_a_jesus.jpg" />
    <rating>
      <value>R</value>
    </rating>
  </programme>
  <programme start="20210315230000 -0600" stop="20210315235000 -0600" channel="Canal Frecuencia Latina">
    <title lang="es">90 Noche</title>
  </programme>
  <programme start="20210315235000 -0600" stop="20210316003000 -0600" channel="Canal Frecuencia Latina">
    <title lang="es">Más vale tarde</title>
  </programme>
  <programme start="20210316235000 -0600" stop="20210317003000 -0600" channel="Canal Frecuencia Latina">
    <title lang="es">Más vale tarde</title>
  </programme>
  <programme start="20210317003000 -0600" stop="20210317005000 -0600" channel="Canal Frecuencia Latina">
    <title lang="es">Contigo seleccion</title>
  </programme>
  <programme start="20210317005000 -0600" stop="20210317013000 -0600" channel="Canal Frecuencia Latina">
    <title lang="es">Confesiones, historias de la vida misma</title>
  </programme>
  <programme start="20210317013000 -0600" stop="20210317043000 -0600" channel="Canal Frecuencia Latina">
    <title lang="es">Espacio alquilado</title>
  </programme>
  <programme start="20210317043000 -0600" stop="20210317050000 -0600" channel="Canal Frecuencia Latina">
    <title lang="es">Escándalo</title>
  </programme>
  <programme start="20210317050000 -0600" stop="20210317060000 -0600" channel="Canal Frecuencia Latina">
    <title lang="es">Despierta 90 Matinal</title>
  </programme>
  <programme start="20210317060000 -0600" stop="20210317070000 -0600" channel="Canal Frecuencia Latina">
    <title lang="es">90 Matinal Nacional</title>
  </programme>
  <programme start="20210317070000 -0600" stop="20210317090000 -0600" channel="Canal Frecuencia Latina">
    <title lang="es">90 Matinal</title>
  </programme>
  <programme start="20210317090000 -0600" stop="20210317120000 -0600" channel="Canal Frecuencia Latina">
    <title lang="es">Mujeres al mando</title>
  </programme>
  <programme start="20210317120000 -0600" stop="20210317143000 -0600" channel="Canal Frecuencia Latina">
    <title lang="es">90 Mediodía</title>
  </programme>
  <programme start="20210317143000 -0600" stop="20210317160000 -0600" channel="Canal Frecuencia Latina">
    <title lang="es">Caso Cerrado</title>
  </programme>
  <programme start="20210317160000 -0600" stop="20210317164500 -0600" channel="Canal Frecuencia Latina">
    <title lang="es">Yo soy Betty, la fea</title>
  </programme>
  <programme start="20210317164500 -0600" stop="20210317173000 -0600" channel="Canal Frecuencia Latina">
    <title lang="es">Guerra de Rosas</title>
  </programme>
  <programme start="20210317173000 -0600" stop="20210317190000 -0600" channel="Canal Frecuencia Latina">
    <title lang="es">Caso Cerrado</title>
  </programme>
  <programme start="20210317190000 -0600" stop="20210317203000 -0600" channel="Canal Frecuencia Latina">
    <title lang="es">90 Central</title>
  </programme>
  <programme start="20210317203000 -0600" stop="20210317220000 -0600" channel="Canal Frecuencia Latina">
    <title lang="es">Yo soy</title>
  </programme>
  <programme start="20210317220000 -0600" stop="20210317230000 -0600" channel="Canal Frecuencia Latina">
    <title lang="es">Matar a Jesús</title>
    <title lang="xx">Matar a Jesús</title>
    <desc lang="es">Una joven de 22 años que tras la muerte de su padre conoce al asesino, a partir de ese momento se verá forzada a definir los límites de su propia humanidad.</desc>
    <credits>
      <actor>Natasha Jaramillo</actor>
      <actor>Giovanny Rodríguez</actor>
      <actor>Camilo Escobar</actor>
      <actor>Carmenza Cossio</actor>
      <actor>Juan Pablo Trujillo</actor>
      <actor>José David Medina</actor>
      <actor>Juan Camilo Cárdenas</actor>
    </credits>
    <date>2018</date>
    <category lang="es">Película</category>
    <icon src="https://imagenes.gatotv.com/categorias/peliculas/miniatura/matar_a_jesus.jpg" />
    <rating>
      <value>R</value>
    </rating>
  </programme>
  <programme start="20210317230000 -0600" stop="20210317235000 -0600" channel="Canal Frecuencia Latina">
    <title lang="es">90 Noche</title>
  </programme>
  <programme start="20210315000500 -0600" stop="20210315003000 -0600" channel="Canal Teleamazonas ">
    <title lang="es">En Corto</title>
  </programme>
  <programme start="20210315003000 -0600" stop="20210315013000 -0600" channel="Canal Teleamazonas ">
    <title lang="es">Mitos y verdades</title>
  </programme>
  <programme start="20210315013000 -0600" stop="20210315021500 -0600" channel="Canal Teleamazonas ">
    <title lang="es">Día a día</title>
  </programme>
  <programme start="20210315021500 -0600" stop="20210315024500 -0600" channel="Canal Teleamazonas ">
    <title lang="es">24 Horas</title>
  </programme>
  <programme start="20210315024500 -0600" stop="20210315031500 -0600" channel="Canal Teleamazonas ">
    <title lang="es">Deporte Total</title>
  </programme>
  <programme start="20210315031500 -0600" stop="20210315033000 -0600" channel="Canal Teleamazonas ">
    <title lang="es">En Corto</title>
  </programme>
  <programme start="20210315033000 -0600" stop="20210315041500 -0600" channel="Canal Teleamazonas ">
    <title lang="es">Hora 25</title>
  </programme>
  <programme start="20210315041500 -0600" stop="20210315050000 -0600" channel="Canal Teleamazonas ">
    <title lang="es">Vecinos</title>
  </programme>
  <programme start="20210315050000 -0600" stop="20210315060000 -0600" channel="Canal Teleamazonas ">
    <title lang="es">No-Ticias</title>
  </programme>
  <programme start="20210315060000 -0600" stop="20210315070000 -0600" channel="Canal Teleamazonas ">
    <title lang="es">24 Horas</title>
  </programme>
  <programme start="20210315070000 -0600" stop="20210315073000 -0600" channel="Canal Teleamazonas ">
    <title lang="es">Los Desayunos De 24 Horas</title>
  </programme>
  <programme start="20210315073000 -0600" stop="20210315090000 -0600" channel="Canal Teleamazonas ">
    <title lang="es">24 Horas</title>
  </programme>
  <programme start="20210315090000 -0600" stop="20210315093000 -0600" channel="Canal Teleamazonas ">
    <title lang="es">Soy yo</title>
  </programme>
  <programme start="20210315093000 -0600" stop="20210315113000 -0600" channel="Canal Teleamazonas ">
    <title lang="es">Madre</title>
  </programme>
  <programme start="20210315113000 -0600" stop="20210315123000 -0600" channel="Canal Teleamazonas ">
    <title lang="es">Boys Over Flowers</title>
  </programme>
  <programme start="20210315123000 -0600" stop="20210315132500 -0600" channel="Canal Teleamazonas ">
    <title lang="es">Tres por tres</title>
  </programme>
  <programme start="20210315132500 -0600" stop="20210315140500 -0600" channel="Canal Teleamazonas ">
    <title lang="es">24 Horas</title>
  </programme>
  <programme start="20210315140500 -0600" stop="20210315143500 -0600" channel="Canal Teleamazonas ">
    <title lang="es">Comunidad</title>
  </programme>
  <programme start="20210315143500 -0600" stop="20210315144500 -0600" channel="Canal Teleamazonas ">
    <title lang="es">En Corto</title>
  </programme>
  <programme start="20210315144500 -0600" stop="20210315150000 -0600" channel="Canal Teleamazonas ">
    <title lang="es">Deporte Total</title>
  </programme>
  <programme start="20210315150000 -0600" stop="20210315160000 -0600" channel="Canal Teleamazonas ">
    <title lang="es">Bob Esponja</title>
  </programme>
  <programme start="20210315160000 -0600" stop="20210315163000 -0600" channel="Canal Teleamazonas ">
    <title lang="es">Los Pingüinos de Madagascar</title>
    <title lang="xx">The Penguins of Madagascar</title>
    <desc lang="es">Cuatro pingüinos que viven en el zoológico de Central Park en Nueva York deben usar sus habilidades de comando de primer nivel para resolver misiones.</desc>
    <date>2008</date>
    <category lang="es">Animación</category>
    <icon src="https://imagenes.gatotv.com/categorias/caricaturas/miniatura/los_pinguinos_de_madagascar.jpg" />
    <rating>
      <value>TV-PG</value>
    </rating>
  </programme>
  <programme start="20210315163000 -0600" stop="20210315170000 -0600" channel="Canal Teleamazonas ">
    <title lang="es">Doraemon</title>
  </programme>
  <programme start="20210315170000 -0600" stop="20210315180000 -0600" channel="Canal Teleamazonas ">
    <title lang="es">Futurama</title>
  </programme>
  <programme start="20210315180000 -0600" stop="20210315190000 -0600" channel="Canal Teleamazonas ">
    <title lang="es">Nuevo rico, nuevo pobre</title>
  </programme>
  <programme start="20210315190000 -0600" stop="20210315200000 -0600" channel="Canal Teleamazonas ">
    <title lang="es">Los Simpson</title>
    <desc lang="es">Una parodia satírica que cuenta las aventuras de los famosos personajes Homero, Marge, Bart, Lisa y Maggie de Springfield.</desc>
    <date>1989</date>
    <category lang="es">Caricatura</category>
    <category lang="es">Programa</category>
    <category lang="es">Serie</category>
    <icon src="https://imagenes.gatotv.com/categorias/programas/miniatura/los_simpson.png" />
  </programme>
  <programme start="20210315200000 -0600" stop="20210315210000 -0600" channel="Canal Teleamazonas ">
    <title lang="es">24 Horas</title>
  </programme>
  <programme start="20210315210000 -0600" stop="20210315220000 -0600" channel="Canal Teleamazonas ">
    <title lang="es">El Doctor milagro</title>
  </programme>
  <programme start="20210315220000 -0600" stop="20210315230000 -0600" channel="Canal Teleamazonas ">
    <title lang="es">Enfermeras</title>
  </programme>
  <programme start="20210315230000 -0600" stop="20210315231000 -0600" channel="Canal Teleamazonas ">
    <title lang="es">La ley secreta</title>
  </programme>
  <programme start="20210315231000 -0600" stop="20210316001500 -0600" channel="Canal Teleamazonas ">
    <title lang="es">Perseguidos</title>
    <desc lang="es">Un capo perseguido por la justicia ha sido traicionado, ahora las autoridades por fin logran seguirle el rastro y desean capturarlo vivo o muerto.</desc>
    <credits>
      <actor>Mauricio Islas</actor>
      <actor>Irán Castillo</actor>
      <actor>Marisol del Olmo</actor>
      <actor>Sara Maldonado</actor>
      <actor>Miguel Rodarte</actor>
      <actor>Gerardo Taracena</actor>
      <actor>Roberto Mateos</actor>
      <actor>Alejandro de la Madrid</actor>
      <producer>Perla Martínez Legorreta</producer>
      <producer>Aurelio Valcárcel Carrol</producer>
    </credits>
    <date>2016</date>
    <category lang="es">Serie</category>
    <icon src="https://imagenes.gatotv.com/categorias/programas/miniatura/perseguidos.jpg" />
    <rating>
      <value>TV-14</value>
    </rating>
  </programme>
  <programme start="20210316231000 -0600" stop="20210317001500 -0600" channel="Canal Teleamazonas ">
    <title lang="es">Perseguidos</title>
    <desc lang="es">Un capo perseguido por la justicia ha sido traicionado, ahora las autoridades por fin logran seguirle el rastro y desean capturarlo vivo o muerto.</desc>
    <credits>
      <actor>Mauricio Islas</actor>
      <actor>Irán Castillo</actor>
      <actor>Marisol del Olmo</actor>
      <actor>Sara Maldonado</actor>
      <actor>Miguel Rodarte</actor>
      <actor>Gerardo Taracena</actor>
      <actor>Roberto Mateos</actor>
      <actor>Alejandro de la Madrid</actor>
      <producer>Perla Martínez Legorreta</producer>
      <producer>Aurelio Valcárcel Carrol</producer>
    </credits>
    <date>2016</date>
    <category lang="es">Serie</category>
    <icon src="https://imagenes.gatotv.com/categorias/programas/miniatura/perseguidos.jpg" />
    <rating>
      <value>TV-14</value>
    </rating>
  </programme>
  <programme start="20210317001500 -0600" stop="20210317011500 -0600" channel="Canal Teleamazonas ">
    <title lang="es">Homeland</title>
    <title lang="xx">Homeland</title>
    <desc lang="es">Una oficial de la CIA se convence a si misma que el rescate de un soldado dado por muerto años atrás se trata de un complot de Al Qaeda en suelo americano.</desc>
    <credits>
      <actor>Claire Danes</actor>
      <actor>Damian Lewis</actor>
      <actor>Morena Baccarin</actor>
      <actor>David Harewood</actor>
      <actor>Diego Klattenhoff</actor>
      <actor>Jackson Pace</actor>
      <actor>Morgan Saylor</actor>
      <actor>Mandy Patinkin</actor>
      <producer>Lauren White</producer>
      <producer>Katie O'Hara</producer>
      <composer>Sean Callery</composer>
    </credits>
    <date>2011</date>
    <category lang="es">Serie</category>
    <icon src="https://imagenes.gatotv.com/categorias/programas/miniatura/homeland.jpg" />
    <rating>
      <value>TV-MA</value>
    </rating>
  </programme>
  <programme start="20210317011500 -0600" stop="20210317020000 -0600" channel="Canal Teleamazonas ">
    <title lang="es">Vivos</title>
  </programme>
  <programme start="20210317020000 -0600" stop="20210317023000 -0600" channel="Canal Teleamazonas ">
    <title lang="es">24 Horas</title>
  </programme>
  <programme start="20210317023000 -0600" stop="20210317024500 -0600" channel="Canal Teleamazonas ">
    <title lang="es">24 horas</title>
  </programme>
  <programme start="20210317024500 -0600" stop="20210317033000 -0600" channel="Canal Teleamazonas ">
    <title lang="es">Divino niño</title>
  </programme>
  <programme start="20210317033000 -0600" stop="20210317040000 -0600" channel="Canal Teleamazonas ">
    <title lang="es">Educa</title>
  </programme>
  <programme start="20210317040000 -0600" stop="20210317041500 -0600" channel="Canal Teleamazonas ">
    <title lang="es">Camaramanía</title>
  </programme>
  <programme start="20210317170000 -0600" stop="20210317180000 -0600" channel="Canal Teleamazonas ">
    <title lang="es">Futurama</title>
  </programme>
  <programme start="20210318001500 -0600" stop="20210318011500 -0600" channel="Canal Teleamazonas ">
    <title lang="es">C.S.I. Miami</title>
    <title lang="xx">CSI: Miami</title>
    <desc lang="es">Investigadores con grandes habilidades salen a las calles, playas y pantanos de Miami con un Humvee y la capacidad de arrestar a cualquier sospechoso.</desc>
    <credits>
      <actor>David Caruso</actor>
      <actor>Emily Procter</actor>
      <actor>Adam Rodriguez</actor>
      <actor>Khandi Alexander</actor>
      <actor>Rory Cochrane</actor>
      <actor>Kim Delaney</actor>
      <actor>Sofia Milos</actor>
      <actor>Jonathan Togo</actor>
      <producer>Marc Dube</producer>
      <composer>Kevin Kiner</composer>
      <composer>Jeff Cardoni</composer>
    </credits>
    <date>2002</date>
    <category lang="es">Serie</category>
    <icon src="https://imagenes.gatotv.com/categorias/programas/miniatura/csi_miami.jpg" />
    <rating>
      <value>TV-14</value>
    </rating>
  </programme>
  <programme start="20210319001500 -0600" stop="20210319011500 -0600" channel="Canal Teleamazonas ">
    <title lang="es">C.S.I. Las Vegas</title>
    <desc lang="es">Investigadores buscan las verdades de los asesinatos en la ciudad de Las Vegas demostrando a los criminales que salirse con la suya es mucho más difícil.</desc>
    <credits>
      <actor>William Petersen</actor>
      <actor>Marg Helgenberger</actor>
      <actor>Gary Dourdan</actor>
      <actor>George Eads</actor>
      <actor>Paul Guilfoyle</actor>
      <actor>Jorja Fox</actor>
      <actor>Eric Szmanda</actor>
      <actor>Robert David Hall</actor>
      <composer>John M. Keane</composer>
      <composer>Jamie Shields</composer>
    </credits>
    <date>2000</date>
    <category lang="es">Serie</category>
    <icon src="https://imagenes.gatotv.com/categorias/programas/miniatura/csi_crime_scene_investigation.jpg" />
    <rating>
      <value>TV-14</value>
    </rating>
  </programme>
  <programme start="20210315010000 -0600" stop="20210315020000 -0600" channel="Canal RTS">
    <title lang="es">Números</title>
  </programme>
  <programme start="20210315020000 -0600" stop="20210315030000 -0600" channel="Canal RTS">
    <title lang="es">Navy NCIS</title>
  </programme>
  <programme start="20210315030000 -0600" stop="20210315040000 -0600" channel="Canal RTS">
    <title lang="es">Navy NCIS</title>
  </programme>
  <programme start="20210315040000 -0600" stop="20210315060000 -0600" channel="Canal RTS">
    <title lang="es">Los endemoniados del ring</title>
  </programme>
  <programme start="20210315060000 -0600" stop="20210315070000 -0600" channel="Canal RTS">
    <title lang="es">El despertar de La Noticia</title>
  </programme>
  <programme start="20210315070000 -0600" stop="20210315080000 -0600" channel="Canal RTS">
    <title lang="es">La noticia</title>
  </programme>
  <programme start="20210315080000 -0600" stop="20210315093000 -0600" channel="Canal RTS">
    <title lang="es">La noticia en la comunidad</title>
  </programme>
  <programme start="20210315093000 -0600" stop="20210315110000 -0600" channel="Canal RTS">
    <title lang="es">Noticias de la mañana</title>
  </programme>
  <programme start="20210315110000 -0600" stop="20210315120000 -0600" channel="Canal RTS">
    <title lang="es">Mujer, casos de la vida real</title>
  </programme>
  <programme start="20210315120000 -0600" stop="20210315130000 -0600" channel="Canal RTS">
    <title lang="es">Karadayi</title>
  </programme>
  <programme start="20210315130000 -0600" stop="20210315140000 -0600" channel="Canal RTS">
    <title lang="es">Rosa de Guadalupe</title>
  </programme>
  <programme start="20210315140000 -0600" stop="20210315150000 -0600" channel="Canal RTS">
    <title lang="es">Como dice el dicho</title>
  </programme>
  <programme start="20210315150000 -0600" stop="20210315160000 -0600" channel="Canal RTS">
    <title lang="es">EDUCA La hora educativa</title>
  </programme>
  <programme start="20210315160000 -0600" stop="20210315170000 -0600" channel="Canal RTS">
    <title lang="es">Laura</title>
  </programme>
  <programme start="20210315170000 -0600" stop="20210315180000 -0600" channel="Canal RTS">
    <title lang="es">Mi Marido Tiene Familia</title>
    <title lang="xx">Mi Marido Tiene Familia</title>
    <desc lang="es">La vida de una pareja felizmente casada está por cambiar cuando la verdadera familia de su esposo aparece de repente y todo cambiará para ellos.</desc>
    <credits>
      <actor>Zuria Vega</actor>
      <actor>Daniel Arenas</actor>
      <actor>Diana Bracho</actor>
      <actor>Silvia Pinal</actor>
      <actor>Rafael Inclán</actor>
      <actor>Luz María Jerez</actor>
      <actor>René Casados</actor>
      <actor>Olivia Bucio</actor>
      <writer>"My Husband Got a Family"</writer>
      <producer>Roy Nelson Rojas</producer>
      <producer>Ignacio Ortiz Castillo</producer>
    </credits>
    <date>2017</date>
    <icon src="https://imagenes.gatotv.com/categorias/telenovelas/miniatura/mi_marido_tiene_familia.jpg" />
  </programme>
  <programme start="20210315180000 -0600" stop="20210315190000 -0600" channel="Canal RTS">
    <title lang="es">María la del barrio</title>
  </programme>
  <programme start="20210315190000 -0600" stop="20210315200000 -0600" channel="Canal RTS">
    <title lang="es">Rosa de Guadalupe</title>
  </programme>
  <programme start="20210315200000 -0600" stop="20210315210000 -0600" channel="Canal RTS">
    <title lang="es">Elif</title>
  </programme>
  <programme start="20210315210000 -0600" stop="20210315220000 -0600" channel="Canal RTS">
    <title lang="es">Fugitiva</title>
  </programme>
  <programme start="20210315220000 -0600" stop="20210315230000 -0600" channel="Canal RTS">
    <title lang="es">La noticia</title>
  </programme>
  <programme start="20210315230000 -0600" stop="20210316000000 -0600" channel="Canal RTS">
    <title lang="es">The Walking Dead</title>
    <desc lang="es">Serie que presenta la aclamada serie de historietas de Robert Kirkman con el mismo nombre donde un Sheriff se ve en un mundo lleno de Zombies.</desc>
    <credits>
      <actor>Andrew Lincoln</actor>
      <actor>Jon Bernthal</actor>
      <actor>Sarah Wayne Callies</actor>
      <composer>Bear McCreary</composer>
    </credits>
    <date>2010</date>
    <category lang="es">Serie</category>
    <category lang="es">Programa</category>
    <icon src="https://imagenes.gatotv.com/categorias/programas/miniatura/the_walking_dead.png" />
  </programme>
  <programme start="20210316040000 -0600" stop="20210316050000 -0600" channel="Canal RTS">
    <title lang="es">Ecuador Multicolor</title>
  </programme>
  <programme start="20210316050000 -0600" stop="20210316060000 -0600" channel="Canal RTS">
    <title lang="es">La noticia</title>
  </programme>
  <programme start="20210316060000 -0600" stop="20210316070000 -0600" channel="Canal RTS">
    <title lang="es">El despertar de La Noticia</title>
  </programme>
  <programme start="20210316070000 -0600" stop="20210316080000 -0600" channel="Canal RTS">
    <title lang="es">La noticia</title>
  </programme>
  <programme start="20210316080000 -0600" stop="20210316093000 -0600" channel="Canal RTS">
    <title lang="es">La noticia en la comunidad</title>
  </programme>
  <programme start="20210316093000 -0600" stop="20210316110000 -0600" channel="Canal RTS">
    <title lang="es">Noticias de la mañana</title>
  </programme>
  <programme start="20210316110000 -0600" stop="20210316120000 -0600" channel="Canal RTS">
    <title lang="es">Mujer, casos de la vida real</title>
  </programme>
  <programme start="20210316120000 -0600" stop="20210316130000 -0600" channel="Canal RTS">
    <title lang="es">Karadayi</title>
  </programme>
  <programme start="20210316130000 -0600" stop="20210316140000 -0600" channel="Canal RTS">
    <title lang="es">Rosa de Guadalupe</title>
  </programme>
  <programme start="20210316140000 -0600" stop="20210316150000 -0600" channel="Canal RTS">
    <title lang="es">Como dice el dicho</title>
  </programme>
  <programme start="20210316150000 -0600" stop="20210316160000 -0600" channel="Canal RTS">
    <title lang="es">EDUCA La hora educativa</title>
  </programme>
  <programme start="20210316160000 -0600" stop="20210316170000 -0600" channel="Canal RTS">
    <title lang="es">Laura</title>
  </programme>
  <programme start="20210316170000 -0600" stop="20210316180000 -0600" channel="Canal RTS">
    <title lang="es">Mi Marido Tiene Familia</title>
    <title lang="xx">Mi Marido Tiene Familia</title>
    <desc lang="es">La vida de una pareja felizmente casada está por cambiar cuando la verdadera familia de su esposo aparece de repente y todo cambiará para ellos.</desc>
    <credits>
      <actor>Zuria Vega</actor>
      <actor>Daniel Arenas</actor>
      <actor>Diana Bracho</actor>
      <actor>Silvia Pinal</actor>
      <actor>Rafael Inclán</actor>
      <actor>Luz María Jerez</actor>
      <actor>René Casados</actor>
      <actor>Olivia Bucio</actor>
      <writer>"My Husband Got a Family"</writer>
      <producer>Roy Nelson Rojas</producer>
      <producer>Ignacio Ortiz Castillo</producer>
    </credits>
    <date>2017</date>
    <icon src="https://imagenes.gatotv.com/categorias/telenovelas/miniatura/mi_marido_tiene_familia.jpg" />
  </programme>
  <programme start="20210316180000 -0600" stop="20210316190000 -0600" channel="Canal RTS">
    <title lang="es">María la del barrio</title>
  </programme>
  <programme start="20210316190000 -0600" stop="20210316200000 -0600" channel="Canal RTS">
    <title lang="es">Rosa de Guadalupe</title>
  </programme>
  <programme start="20210316200000 -0600" stop="20210316210000 -0600" channel="Canal RTS">
    <title lang="es">Elif</title>
  </programme>
  <programme start="20210316210000 -0600" stop="20210316220000 -0600" channel="Canal RTS">
    <title lang="es">Fugitiva</title>
  </programme>
  <programme start="20210316220000 -0600" stop="20210316230000 -0600" channel="Canal RTS">
    <title lang="es">La noticia</title>
  </programme>
  <programme start="20210316230000 -0600" stop="20210317000000 -0600" channel="Canal RTS">
    <title lang="es">The Walking Dead</title>
    <desc lang="es">Serie que presenta la aclamada serie de historietas de Robert Kirkman con el mismo nombre donde un Sheriff se ve en un mundo lleno de Zombies.</desc>
    <credits>
      <actor>Andrew Lincoln</actor>
      <actor>Jon Bernthal</actor>
      <actor>Sarah Wayne Callies</actor>
      <composer>Bear McCreary</composer>
    </credits>
    <date>2010</date>
    <category lang="es">Serie</category>
    <category lang="es">Programa</category>
    <icon src="https://imagenes.gatotv.com/categorias/programas/miniatura/the_walking_dead.png" />
  </programme>
</tv>